string_extract.py
String_Extract-1.1.5.dist-info/LICENSE
String_Extract-1.1.5.dist-info/METADATA
String_Extract-1.1.5.dist-info/WHEEL
String_Extract-1.1.5.dist-info/top_level.txt
String_Extract-1.1.5.dist-info/RECORD
