Metadata-Version: 2.1
Name: String-Extract
Version: 1.1.5
Summary: String Extractor
Home-page: UNKNOWN
Author: Fayas Noushad
License: MIT
Project-URL: Tracker, https://github.com/FayasNoushad/String-Extract/issues
Project-URL: Source, https://github.com/FayasNoushad/String-Extract
Platform: UNKNOWN
Classifier: Intended Audience :: Developers
Classifier: Natural Language :: English
Classifier: Programming Language :: Python
Classifier: License :: OSI Approved :: MIT License
Classifier: Operating System :: OS Independent
Requires-Python: >=3.6
License-File: LICENSE
